envx/__init__.py
envx-1.0.2.dist-info/LICENSE
envx-1.0.2.dist-info/METADATA
envx-1.0.2.dist-info/WHEEL
envx-1.0.2.dist-info/top_level.txt
envx-1.0.2.dist-info/RECORD
