Metadata-Version: 2.1
Name: envx
Version: 1.0.2
Summary: 便捷的环境文件读取
Home-page: https://gitee.com/ZeroSeeker/envx
Author: ZeroSeeker
Author-email: zeroseeker@foxmail.com
Classifier: Programming Language :: Python :: 3
Classifier: License :: OSI Approved :: MIT License
Classifier: Operating System :: OS Independent
License-File: LICENSE
